scores/__init__.py
scores/functions.py
scores/sample_data.py
scores/typing.py
scores/utils.py
scores/categorical/__init__.py
scores/categorical/binary_impl.py
scores/categorical/contingency_impl.py
scores/categorical/multicategorical_impl.py
scores/categorical/risk_matrix_impl.py
scores/continuous/__init__.py
scores/continuous/consistent_impl.py
scores/continuous/flip_flop_impl.py
scores/continuous/interval_impl.py
scores/continuous/nse_impl.py
scores/continuous/quantile_loss_impl.py
scores/continuous/standard_impl.py
scores/continuous/threshold_weighted_impl.py
scores/continuous/correlation/__init__.py
scores/continuous/correlation/correlation_impl.py
scores/emerging/__init__.py
scores/fast/__init__.py
scores/fast/fss/__init__.py
scores/fast/fss/backend.py
scores/fast/fss/fss_backends.py
scores/fast/fss/fss_numba.py
scores/fast/fss/fss_numpy.py
scores/fast/fss/typing.py
scores/pandas/__init__.py
scores/pandas/continuous.py
scores/pandas/typing.py
scores/plotdata/__init__.py
scores/plotdata/murphy_impl.py
scores/plotdata/qq_impl.py
scores/plotdata/roc_impl.py
scores/probability/__init__.py
scores/probability/brier_impl.py
scores/probability/checks.py
scores/probability/crps_impl.py
scores/probability/crps_numba.py
scores/processing/__init__.py
scores/processing/aggregation.py
scores/processing/block_bootstrap_impl.py
scores/processing/discretise.py
scores/processing/isoreg_impl.py
scores/processing/matching.py
scores/processing/cdf/__init__.py
scores/processing/cdf/cdf_functions.py
scores/spatial/__init__.py
scores/spatial/fss_impl.py
scores/stats/__init__.py
scores/stats/statistical_tests/__init__.py
scores/stats/statistical_tests/acovf.py
scores/stats/statistical_tests/diebold_mariano_impl.py
scores-2.4.0.dist-info/METADATA
scores-2.4.0.dist-info/WHEEL
scores-2.4.0.dist-info/licenses/LICENSE
scores-2.4.0.dist-info/licenses/NOTICE.md
scores-2.4.0.dist-info/RECORD
