Metadata-Version: 2.4
Name: scores
Version: 2.4.0
Summary: Scores is a Python package containing mathematical functions for the verification, evaluation and optimisation of forecasts, predictions or models.
Project-URL: Repository, https://github.com/nci/scores
Project-URL: Documentation, https://scores.readthedocs.io/en/stable/
Author-email: Tennessee Leeuwenburg <tennessee.leeuwenburg@bom.gov.au>
License-File: LICENSE
License-File: NOTICE.md
Classifier: License :: OSI Approved :: Apache Software License
Classifier: Operating System :: OS Independent
Classifier: Programming Language :: Python :: 3
Requires-Python: <3.14,>=3.10
Requires-Dist: bottleneck~=1.3
Requires-Dist: pandas~=2.0
Requires-Dist: scipy~=1.13
Requires-Dist: xarray>=2024.1
Provides-Extra: all
Requires-Dist: bandit==1.8.0; extra == 'all'
Requires-Dist: black==24.10.0; extra == 'all'
Requires-Dist: dask; extra == 'all'
Requires-Dist: gcsfs; extra == 'all'
Requires-Dist: h5netcdf; extra == 'all'
Requires-Dist: jupyterlab; extra == 'all'
Requires-Dist: matplotlib; extra == 'all'
Requires-Dist: mypy==1.13.0; extra == 'all'
Requires-Dist: nbmake; extra == 'all'
Requires-Dist: numba; extra == 'all'
Requires-Dist: pandas-stubs; extra == 'all'
Requires-Dist: plotly; extra == 'all'
Requires-Dist: pre-commit; extra == 'all'
Requires-Dist: pylint==3.3.1; extra == 'all'
Requires-Dist: pytest; extra == 'all'
Requires-Dist: pytest-cov; extra == 'all'
Requires-Dist: pytest-watch; extra == 'all'
Requires-Dist: rasterio; extra == 'all'
Requires-Dist: rioxarray; extra == 'all'
Requires-Dist: zarr; extra == 'all'
Provides-Extra: dev
Requires-Dist: bandit==1.8.0; extra == 'dev'
Requires-Dist: black==24.10.0; extra == 'dev'
Requires-Dist: dask; extra == 'dev'
Requires-Dist: h5netcdf; extra == 'dev'
Requires-Dist: mypy==1.13.0; extra == 'dev'
Requires-Dist: nbmake; extra == 'dev'
Requires-Dist: pandas-stubs; extra == 'dev'
Requires-Dist: pre-commit; extra == 'dev'
Requires-Dist: pylint==3.3.1; extra == 'dev'
Requires-Dist: pytest; extra == 'dev'
Requires-Dist: pytest-cov; extra == 'dev'
Requires-Dist: pytest-watch; extra == 'dev'
Provides-Extra: fast
Requires-Dist: numba; extra == 'fast'
Provides-Extra: maintainer
Requires-Dist: build; extra == 'maintainer'
Requires-Dist: hatch; extra == 'maintainer'
Requires-Dist: ipywidgets; extra == 'maintainer'
Requires-Dist: myst-parser; extra == 'maintainer'
Requires-Dist: nbsphinx; extra == 'maintainer'
Requires-Dist: pandoc; extra == 'maintainer'
Requires-Dist: pip-tools; extra == 'maintainer'
Requires-Dist: sphinx; extra == 'maintainer'
Requires-Dist: sphinx-book-theme; extra == 'maintainer'
Requires-Dist: sphinx-gallery; extra == 'maintainer'
Requires-Dist: twine; extra == 'maintainer'
Provides-Extra: tutorial
Requires-Dist: dask; extra == 'tutorial'
Requires-Dist: gcsfs; extra == 'tutorial'
Requires-Dist: h5netcdf; extra == 'tutorial'
Requires-Dist: jupyterlab; extra == 'tutorial'
Requires-Dist: matplotlib; extra == 'tutorial'
Requires-Dist: plotly; extra == 'tutorial'
Requires-Dist: rasterio; extra == 'tutorial'
Requires-Dist: rioxarray; extra == 'tutorial'
Requires-Dist: zarr; extra == 'tutorial'
